setup.py
gigioDistributions/Binomialdistribution.py
gigioDistributions/Gaussiandistribution.py
gigioDistributions/Generaldistribution.py
gigioDistributions/__init__.py
gigioDistributions.egg-info/PKG-INFO
gigioDistributions.egg-info/SOURCES.txt
gigioDistributions.egg-info/dependency_links.txt
gigioDistributions.egg-info/not-zip-safe
gigioDistributions.egg-info/top_level.txt