Metadata-Version: 1.0
Name: gigioDistributions
Version: 0.1
Summary: Gaussian and Binomial distributions
Home-page: UNKNOWN
Author: Giovani F, Machado
Author-email: giovani.machado@gmail.com
License: UNKNOWN
Platform: UNKNOWN
